txlogstash/__init__.py
txlogstash/observer.py
txlogstash/test_observer.py
txlogstash-0.1.0.dist-info/DESCRIPTION.rst
txlogstash-0.1.0.dist-info/METADATA
txlogstash-0.1.0.dist-info/RECORD
txlogstash-0.1.0.dist-info/WHEEL
txlogstash-0.1.0.dist-info/metadata.json
txlogstash-0.1.0.dist-info/pbr.json
txlogstash-0.1.0.dist-info/top_level.txt
