Metadata-Version: 2.0
Name: txlogstash
Version: 0.1.0
Summary: A twisted log observer for logstash and similar
Home-page: UNKNOWN
Author: Pierre Tardy
Author-email: tardyp@gmail.com
License: MIT
Keywords: twisted
Requires-Dist: twisted (>=16.0.0)
